{
    "compatibility": [
      ["OS Family", "OS Version", "Status", "Idempotent"],
      ["Fedora", "33", "❌", "❌"],
      ["Ubuntu", "focal", "✅", "❌"]
    ],
    "role_dependencies": [
      ["Role Dependency", "Description"],
      ["<a href='https://google.com'>professormanhattan.homebrew</a>", "Installs Homebrew on macOS"],
      ["<a href='https://bing.com'>professormanhattan.snapd</a>", "Ensures Snap is installed on Linux systems"]
    ],
    "role_description": "An Ansible role that installs juju on nearly any platform",
    "role_description_full_overview": "This repository contains an Ansible role that installs juju on nearly any platform. Better operators for enterprise apps with a full application graph and declarative integration for both Kubernetes and legacy estate.",
    "role_name": "juju",
    "role_pretty_name": "Juju"
  }
