{
    "compatibility": [
      ["OS Family", "OS Version", "Status", "Idempotent"],
      ["Fedora", "33", "❌", "❌"],
      ["Ubuntu", "focal", "✅", "❌"]
    ],
    "role_dependencies": [],
    "role_description": "An Ansible role that Installs tflint on nearly any platform",
    "role_description_full_overview": "This repository contains an Ansible role that installs tflint on nearly any platform. tflint is a framework that can help in finding possible errors for major cloud providers, warn about deprecated syntax and unused declarations and enforce best practices.",
    "role_name": "tflint",
    "role_pretty_name": "tflint",
    "version": "0.0.1"
  }
