{
    "compatibility": [
      ["OS Family", "OS Version", "Status", "Idempotent"],
      ["Fedora", "33", "❌", "❌"],
      ["Ubuntu", "focal", "✅", "❌"]
    ],
    "role_dependencies": [],
    "role_description": "An Ansible role that installs and configures Guacamole for remote-desktop inside a browser",
    "role_description_full_overview": "Apache Guacamole is a clientless remote desktop gateway. It supports standard protocols like VNC, RDP, and SSH.",
    "role_name": "guacamole",
    "role_pretty_name": "Guacamole"
  }
