{
    "compatibility": [
      ["OS Family", "OS Version", "Status", "Idempotent"],
      ["Fedora", "33", "❌", "❌"],
      ["Ubuntu", "focal", "✅", "❌"]
    ],
    "role_dependencies": [],
    "role_description": "An Ansible role that installs Terminus on nearly any platform",
    "role_description_full_overview": "[Terminus](https://termius.com/) is a highly configurable terminal emulator, SSH and serial client for Windows, macOS and Linux.",
    "role_name": "terminus",
    "role_pretty_name": "Terminus"
  }
